examples/__init__.py
examples/simple_example/__init__.py
examples/simple_example/animal.py
examples/simple_example/main.py
examples/simple_example/garden/__init__.py
examples/simple_example/garden/flowers.py
examples/simple_example/garden/garden.py
kiwi_di/__init__.py
kiwi_di/data_types.py
kiwi_di/decorators.py
kiwi_di/exceptions.py
kiwi_di/registry.py
kiwi_di/singleton.py
kiwi_di-0.1.1.dist-info/LICENSE
kiwi_di-0.1.1.dist-info/METADATA
kiwi_di-0.1.1.dist-info/WHEEL
kiwi_di-0.1.1.dist-info/top_level.txt
kiwi_di-0.1.1.dist-info/RECORD
