Metadata-Version: 2.2
Name: kiwi-di
Version: 0.1.1
Summary: A decorator-based dependency injection tool.
Requires-Python: >=3.11, <=3.13
License-File: LICENSE
Dynamic: description
Dynamic: description-content-type
Dynamic: requires-python
Dynamic: summary
